{
  "db_name": "PostgreSQL",
  "query": "\n                SELECT ae.id, ae.event_type, ae.identifier, ae.application_id,\n                       ae.application_name, ae.ip_address, ae.occurred_at\n                FROM auth_events ae\n                JOIN applications a ON ae.application_id = a.id\n                JOIN projects p ON a.project_id = p.id\n                WHERE p.org_id = $1\n                ORDER BY ae.occurred_at DESC, ae.id DESC\n                LIMIT $2\n            ",
  "describe": {
    "columns": [
      {
        "ordinal": 0,
        "name": "id",
        "type_info": "Uuid"
      },
      {
        "ordinal": 1,
        "name": "event_type",
        "type_info": "Text"
      },
      {
        "ordinal": 2,
        "name": "identifier",
        "type_info": "Text"
      },
      {
        "ordinal": 3,
        "name": "application_id",
        "type_info": "Uuid"
      },
      {
        "ordinal": 4,
        "name": "application_name",
        "type_info": "Text"
      },
      {
        "ordinal": 5,
        "name": "ip_address",
        "type_info": "Text"
      },
      {
        "ordinal": 6,
        "name": "occurred_at",
        "type_info": "Timestamptz"
      }
    ],
    "parameters": {
      "Left": [
        "Uuid",
        "Int8"
      ]
    },
    "nullable": [
      false,
      false,
      true,
      true,
      true,
      true,
      false
    ]
  },
  "hash": "536e430865850de7e6a3873ef946d46f8c971759090d0840d37cd630d4fe4cb3"
}
